actinia_core/__init__.py
actinia_core/endpoints.py
actinia_core/health_check.py
actinia_core/main.py
actinia_core/testsuite.py
actinia_core/version.py
actinia_core/cli/__init__.py
actinia_core/cli/actinia_server.py
actinia_core/cli/actinia_user.py
actinia_core/cli/rq_custom_worker.py
actinia_core/cli/webhook_server.py
actinia_core/cli/webhook_server_broken.py
actinia_core/core/__init__.py
actinia_core/core/geodata_download_importer.py
actinia_core/core/google_cloud_storage_access.py
actinia_core/core/grass_init.py
actinia_core/core/grass_modules_list.py
actinia_core/core/interim_results.py
actinia_core/core/kvdb_api_log.py
actinia_core/core/kvdb_fluentd_logger_base.py
actinia_core/core/kvdb_lock.py
actinia_core/core/kvdb_resources.py
actinia_core/core/kvdb_user.py
actinia_core/core/logging_interface.py
actinia_core/core/mapset_merge_utils.py
actinia_core/core/messages_logger.py
actinia_core/core/request_parser.py
actinia_core/core/resource_data_container.py
actinia_core/core/resources_logger.py
actinia_core/core/stac_exporter_interface.py
actinia_core/core/stac_importer_interface.py
actinia_core/core/storage_interface_aws_s3.py
actinia_core/core/storage_interface_base.py
actinia_core/core/storage_interface_filesystem.py
actinia_core/core/storage_interface_gcs.py
actinia_core/core/utils.py
actinia_core/core/common/__init__.py
actinia_core/core/common/api_logger.py
actinia_core/core/common/app.py
actinia_core/core/common/aws_sentinel_interface.py
actinia_core/core/common/config.py
actinia_core/core/common/exceptions.py
actinia_core/core/common/google_satellite_bigquery_interface.py
actinia_core/core/common/keycloak_user.py
actinia_core/core/common/kvdb_base.py
actinia_core/core/common/kvdb_interface.py
actinia_core/core/common/landsat_processing_library.py
actinia_core/core/common/process_chain.py
actinia_core/core/common/process_object.py
actinia_core/core/common/process_queue.py
actinia_core/core/common/sentinel_processing_library.py
actinia_core-7.0.2.dist-info/licenses/AUTHORS.rst
actinia_core-7.0.2.dist-info/licenses/LICENSE.txt
actinia_core-7.0.2.dist-info/METADATA
actinia_core-7.0.2.dist-info/WHEEL
actinia_core-7.0.2.dist-info/entry_points.txt
actinia_core-7.0.2.dist-info/top_level.txt
actinia_core-7.0.2.dist-info/RECORD
