Metadata-Version: 2.4
Name: actinia-core
Version: 7.0.2
Summary: Actinia Core is an open source REST API for scalable, distributed, high performance processing of geographical data that uses mainly GRASS GIS for computational tasks
Author: Carmen Tawalika, Anika Weinmann, Markus Neteler, Guido Riembauer, Markus Metz, Julia Haas, Marc Jansen, Lina Krisztian, Jorge A. Herrera Maldonado, Sören Gebbert, Momen Mawad, and more
Project-URL: Homepage, https://github.com/actinia-org/actinia_core
Project-URL: Tutorial, https://actinia-org.github.io/actinia_core
Project-URL: API_Docs, https://redocly.github.io/redoc/?url=https://actinia.mundialis.de/latest/swagger.json
Keywords: processing,earth observation,cloud-based processing,rest api,gis,grass gis,osgeo
Classifier: License :: OSI Approved :: GNU General Public License v3 (GPLv3)
Classifier: Programming Language :: Python :: 3
Requires-Python: >=3.8
License-File: LICENSE.txt
License-File: AUTHORS.rst
Requires-Dist: actinia-api==3.8.0
Requires-Dist: actinia-rest-lib>=1.0.0
Requires-Dist: actinia-processing-lib>=1.1.1
Requires-Dist: Flask>=3.0.0
Requires-Dist: boto3>=1.6.6
Requires-Dist: colorlog>=4.2.1
Requires-Dist: Flask-HTTPAuth>=3.2.3
Requires-Dist: Flask-RESTful>=0.3.9
Requires-Dist: flask-restful-swagger-2
Requires-Dist: Flask-Cors>=3.0.3
Requires-Dist: fluent-logger>=0.9.4
Requires-Dist: google-cloud>=0.32.0
Requires-Dist: google-cloud-bigquery<=3.40.0
Requires-Dist: google-cloud-storage>=1.6.0
Requires-Dist: gunicorn>=22.0.0
Requires-Dist: matplotlib==3.10.8
Requires-Dist: passlib>=1.7.1
Requires-Dist: psutil>=5.7.0
Requires-Dist: python-json-logger
Requires-Dist: python-keycloak>=2.6.0
Requires-Dist: python-magic>=0.4.15
Requires-Dist: requests>=2.20.0
Requires-Dist: rq==1.16.2
Requires-Dist: setuptools==80.9.0
Requires-Dist: geopandas
Requires-Dist: rasterio==1.5.0
Requires-Dist: pystac==1.14.3
Requires-Dist: PyJWT
Requires-Dist: werkzeug==3.1.5
Requires-Dist: pandas
Requires-Dist: tqdm
Requires-Dist: valkey
Provides-Extra: test
Requires-Dist: pytest; extra == "test"
Requires-Dist: pytest-cov; extra == "test"
Provides-Extra: plugins
Requires-Dist: actinia-metadata-plugin; extra == "plugins"
Requires-Dist: actinia-module-plugin; extra == "plugins"
Requires-Dist: actinia-parallel-plugin; extra == "plugins"
Requires-Dist: actinia-satellite-plugin; extra == "plugins"
Requires-Dist: actinia-stac-plugin; extra == "plugins"
Requires-Dist: actinia-statistic-plugin; extra == "plugins"
Requires-Dist: actinia-tiling-plugin; extra == "plugins"
Dynamic: license-file
